magnitude.py
magnitude-1.1.2.dist-info/METADATA
magnitude-1.1.2.dist-info/WHEEL
magnitude-1.1.2.dist-info/licenses/LICENSE
magnitude-1.1.2.dist-info/RECORD
