Metadata-Version: 2.4
Name: magnitude
Version: 1.1.2
Summary: Python library for computing with numbers with units
Project-URL: Homepage, http://juanreyero.com/open/magnitude/
Project-URL: Documentation, http://juanreyero.com/open/magnitude/
Project-URL: Repository, https://github.com/juanre/magnitude
Project-URL: Issues, https://github.com/juanre/magnitude/issues
Author-email: Juan Reyero <juan@juanreyero.com>
License: MIT
License-File: LICENSE
Keywords: SI,conversion,measurement,physics,units
Classifier: Intended Audience :: Developers
Classifier: Intended Audience :: Science/Research
Classifier: License :: OSI Approved :: MIT License
Classifier: Operating System :: OS Independent
Classifier: Programming Language :: Python :: 3
Classifier: Programming Language :: Python :: 3.9
Classifier: Programming Language :: Python :: 3.10
Classifier: Programming Language :: Python :: 3.11
Classifier: Programming Language :: Python :: 3.12
Classifier: Programming Language :: Python :: 3.13
Classifier: Topic :: Scientific/Engineering
Classifier: Topic :: Software Development :: Libraries
Requires-Python: >=3.9
